py2dylib/__init__.py
py2dylib/__main__.py
py2dylib/package.py
pycodepack-1.0.2.dist-info/LICENSE
pycodepack-1.0.2.dist-info/METADATA
pycodepack-1.0.2.dist-info/WHEEL
pycodepack-1.0.2.dist-info/top_level.txt
pycodepack-1.0.2.dist-info/RECORD
