Metadata-Version: 2.1
Name: pycodepack
Version: 1.0.2
Summary: A tiny tool to convert python files to dynamic libraries
Home-page: https://gitee.com/Marxlp/pycodepack
Author: MarxLP
Author-email: lipi26@foxmail.com
License: UNKNOWN
Project-URL: Bug Tracker, https://gitee.com/Marxlp/pycodepack/issues
Platform: UNKNOWN
Classifier: Programming Language :: Python :: 3
Classifier: License :: OSI Approved :: MIT License
Classifier: Operating System :: OS Independent
Requires-Python: >=3.6
License-File: LICENSE
Requires-Dist: Cython
